mvola_api/__init__.py
mvola_api/api.py
mvola_api/auth.py
mvola_api/data.py
mvola_api/models.py
mvola_api/mvola_merchant_pay_api.py
mvola_api/transaction.py
mvola_api-1.0.1.dist-info/WHEEL
mvola_api-1.0.1.dist-info/METADATA
mvola_api-1.0.1.dist-info/RECORD
